folder_rename.py
FolderRename-1.0.dist-info/DESCRIPTION.rst
FolderRename-1.0.dist-info/METADATA
FolderRename-1.0.dist-info/RECORD
FolderRename-1.0.dist-info/WHEEL
FolderRename-1.0.dist-info/entry_points.txt
FolderRename-1.0.dist-info/metadata.json
FolderRename-1.0.dist-info/top_level.txt
