Metadata-Version: 2.0
Name: FolderRename
Version: 1.0
Summary: A sample Python project to rename folders.
Home-page: https://github.com/pypa/sampleproject
Author: Akhilraj Rajkumar
Author-email: akhilr46@gmail.com
License: MIT
Keywords: sample folder rename for development
Platform: UNKNOWN
Classifier: Development Status :: 3 - Alpha
Classifier: Intended Audience :: Developers
Classifier: Topic :: Software Development :: Build Tools
Classifier: License :: OSI Approved :: MIT License
Classifier: Programming Language :: Python :: 2
Classifier: Programming Language :: Python :: 2.6
Classifier: Programming Language :: Python :: 2.7
Classifier: Programming Language :: Python :: 3
Classifier: Programming Language :: Python :: 3.2
Classifier: Programming Language :: Python :: 3.3
Classifier: Programming Language :: Python :: 3.4
Requires-Python: >=2.6, !=3.0.*, !=3.1.*, !=3.2.*, <4
